LICENSE
MANIFEST.in
README.rst
ez_setup.py
setup.py
cyvcf/__init__.py
cyvcf/filters.py
cyvcf/parser.c
cyvcf/parser.pyx
cyvcf/utils.py
cyvcf/version.py
cyvcf.egg-info/PKG-INFO
cyvcf.egg-info/SOURCES.txt
cyvcf.egg-info/dependency_links.txt
cyvcf.egg-info/top_level.txt
test/test_vcf.py