Metadata-Version: 1.1
Name: cyvcf
Version: 0.1.8
Summary: A fast Python library for VCF files using Cython for speed.
Home-page: none
Author: Aaron Quinlan, James Casbon, John Dougherty, Martin Vermaat, Brent Pedersen
Author-email: arq5x@virginia.edu
License: UNKNOWN
Platform: UNKNOWN
Classifier: Development Status :: 4 - Beta
Classifier: Intended Audience :: Science/Research
Classifier: License :: OSI Approved :: GNU General Public License (GPL)
Classifier: Topic :: Scientific/Engineering :: Bio-Informatics
